{
  "_comment": "Firestore composite indexes for ent2_users. Each of the 7 non-activity ranking fields needs TWO composite indexes: one DESC (for /ranking page orderBy) and one ASC (for getUserRankPositions count with `where field > X`). Firestore requires direction-specific indexes even for count queries. activityDays uses single-field auto-index only. Deploy via `firebase deploy --only firestore:indexes`.",
  "indexes": [
    {
      "collectionGroup": "ent2_users",
      "queryScope": "COLLECTION",
      "fields": [
        { "fieldPath": "truncated", "order": "ASCENDING" },
        { "fieldPath": "totalViews", "order": "DESCENDING" }
      ]
    },
    {
      "collectionGroup": "ent2_users",
      "queryScope": "COLLECTION",
      "fields": [
        { "fieldPath": "truncated", "order": "ASCENDING" },
        { "fieldPath": "totalViews", "order": "ASCENDING" }
      ]
    },
    {
      "collectionGroup": "ent2_users",
      "queryScope": "COLLECTION",
      "fields": [
        { "fieldPath": "truncated", "order": "ASCENDING" },
        { "fieldPath": "totalLikes", "order": "DESCENDING" }
      ]
    },
    {
      "collectionGroup": "ent2_users",
      "queryScope": "COLLECTION",
      "fields": [
        { "fieldPath": "truncated", "order": "ASCENDING" },
        { "fieldPath": "totalLikes", "order": "ASCENDING" }
      ]
    },
    {
      "collectionGroup": "ent2_users",
      "queryScope": "COLLECTION",
      "fields": [
        { "fieldPath": "truncated", "order": "ASCENDING" },
        { "fieldPath": "totalComments", "order": "DESCENDING" }
      ]
    },
    {
      "collectionGroup": "ent2_users",
      "queryScope": "COLLECTION",
      "fields": [
        { "fieldPath": "truncated", "order": "ASCENDING" },
        { "fieldPath": "totalComments", "order": "ASCENDING" }
      ]
    },
    {
      "collectionGroup": "ent2_users",
      "queryScope": "COLLECTION",
      "fields": [
        { "fieldPath": "truncated", "order": "ASCENDING" },
        { "fieldPath": "totalClones", "order": "DESCENDING" }
      ]
    },
    {
      "collectionGroup": "ent2_users",
      "queryScope": "COLLECTION",
      "fields": [
        { "fieldPath": "truncated", "order": "ASCENDING" },
        { "fieldPath": "totalClones", "order": "ASCENDING" }
      ]
    },
    {
      "collectionGroup": "ent2_users",
      "queryScope": "COLLECTION",
      "fields": [
        { "fieldPath": "truncated", "order": "ASCENDING" },
        { "fieldPath": "totalBlocks", "order": "DESCENDING" }
      ]
    },
    {
      "collectionGroup": "ent2_users",
      "queryScope": "COLLECTION",
      "fields": [
        { "fieldPath": "truncated", "order": "ASCENDING" },
        { "fieldPath": "totalBlocks", "order": "ASCENDING" }
      ]
    },
    {
      "collectionGroup": "ent2_users",
      "queryScope": "COLLECTION",
      "fields": [
        { "fieldPath": "truncated", "order": "ASCENDING" },
        { "fieldPath": "popularCount", "order": "DESCENDING" }
      ]
    },
    {
      "collectionGroup": "ent2_users",
      "queryScope": "COLLECTION",
      "fields": [
        { "fieldPath": "truncated", "order": "ASCENDING" },
        { "fieldPath": "popularCount", "order": "ASCENDING" }
      ]
    },
    {
      "collectionGroup": "ent2_users",
      "queryScope": "COLLECTION",
      "fields": [
        { "fieldPath": "truncated", "order": "ASCENDING" },
        { "fieldPath": "staffCount", "order": "DESCENDING" }
      ]
    },
    {
      "collectionGroup": "ent2_users",
      "queryScope": "COLLECTION",
      "fields": [
        { "fieldPath": "truncated", "order": "ASCENDING" },
        { "fieldPath": "staffCount", "order": "ASCENDING" }
      ]
    }
  ],
  "fieldOverrides": []
}
